flask_attachments/__about__.py
flask_attachments/__init__.py
flask_attachments/_version.py
flask_attachments/cli.py
flask_attachments/compression.py
flask_attachments/extension.py
flask_attachments/models.py
flask_attachments/py.typed
flask_attachments/services.py
flask_attachments/views.py
flask_attachments-0.2.2.dist-info/METADATA
flask_attachments-0.2.2.dist-info/WHEEL
flask_attachments-0.2.2.dist-info/licenses/AUTHORS.rst
flask_attachments-0.2.2.dist-info/licenses/LICENSE
flask_attachments-0.2.2.dist-info/RECORD
